MANIFEST.in
README.md
setup.py
topper/__init__.py
topper/__main__.py
topper/file_io.py
topper/process.py
topper.egg-info/PKG-INFO
topper.egg-info/SOURCES.txt
topper.egg-info/dependency_links.txt
topper.egg-info/entry_points.txt
topper.egg-info/top_level.txt
topper/resources/countries.json
topper/utils/__init__.py
topper/utils/logging.py
topper/utils/parser.py