Metadata-Version: 2.1
Name: topper
Version: 1.0.1
Summary: An application computing top songs by country or user_id over 7 days
Home-page: UNKNOWN
Author: Baptiste Azéma
Author-email: baptiste@azema.tech
License: LICENSE
Platform: UNKNOWN
